{
    "id":  "omraden_befolkning",
    "titel":  "Befolkning per DeSO och RegSO, senaste år",
    "beskrivning":  "Folkmängd och åldersstruktur per statistikområde - grund för analys på delområdesnivå.",
    "enhet":  "antal personer",
    "kalla":  {
                  "myndighet":  "SCB",
                  "tabell":  "TAB6574",
                  "licens":  "CC0",
                  "hamtad":  "2026-07-06T23:58:00",
                  "url":  "https://api.scb.se/OV0104/v2beta/api/v2/tables/TAB6574/data?valueCodes[Region]=1780*\u0026valueCodes[Alder]=*\u0026valueCodes[Kon]=1%2B2\u0026valueCodes[ContentsCode]=000007Y7\u0026valueCodes[Tid]=top(1)\u0026outputFormat=json-stat2"
              },
    "innehall":  {
                     "ar":  "2025",
                     "deso":  {
                                  "1780A0010":  {
                                                    "totalt":  1136,
                                                    "andel019":  22,
                                                    "andel65":  24.9
                                                },
                                  "1780A0020":  {
                                                    "totalt":  2040,
                                                    "andel019":  23,
                                                    "andel65":  25.9
                                                },
                                  "1780A0030":  {
                                                    "totalt":  1326,
                                                    "andel019":  26.6,
                                                    "andel65":  17.3
                                                },
                                  "1780A0040":  {
                                                    "totalt":  1478,
                                                    "andel019":  24.1,
                                                    "andel65":  20.2
                                                },
                                  "1780A0050":  {
                                                    "totalt":  895,
                                                    "andel019":  18.8,
                                                    "andel65":  26.1
                                                },
                                  "1780A0060":  {
                                                    "totalt":  1719,
                                                    "andel019":  20.3,
                                                    "andel65":  26.6
                                                },
                                  "1780B2010":  {
                                                    "totalt":  1249,
                                                    "andel019":  20.1,
                                                    "andel65":  29.8
                                                },
                                  "1780B2020":  {
                                                    "totalt":  1840,
                                                    "andel019":  21.8,
                                                    "andel65":  22.6
                                                },
                                  "1780B3010":  {
                                                    "totalt":  2130,
                                                    "andel019":  19.7,
                                                    "andel65":  27.9
                                                },
                                  "1780B4010":  {
                                                    "totalt":  958,
                                                    "andel019":  22.7,
                                                    "andel65":  25.8
                                                },
                                  "1780C1010":  {
                                                    "totalt":  2340,
                                                    "andel019":  22.8,
                                                    "andel65":  20.9
                                                },
                                  "1780C1020":  {
                                                    "totalt":  1889,
                                                    "andel019":  19,
                                                    "andel65":  31.3
                                                },
                                  "1780C1030":  {
                                                    "totalt":  2658,
                                                    "andel019":  20,
                                                    "andel65":  19.8
                                                },
                                  "1780C1041":  {
                                                    "totalt":  1591,
                                                    "andel019":  10.8,
                                                    "andel65":  37.3
                                                },
                                  "1780C1042":  {
                                                    "totalt":  1027,
                                                    "andel019":  7.5,
                                                    "andel65":  16.8
                                                },
                                  "1780C1043":  {
                                                    "totalt":  1938,
                                                    "andel019":  8.3,
                                                    "andel65":  13.7
                                                },
                                  "1780C1044":  {
                                                    "totalt":  1629,
                                                    "andel019":  10,
                                                    "andel65":  16.1
                                                },
                                  "1780C1050":  {
                                                    "totalt":  1660,
                                                    "andel019":  8.3,
                                                    "andel65":  31.1
                                                },
                                  "1780C1060":  {
                                                    "totalt":  1597,
                                                    "andel019":  17.3,
                                                    "andel65":  19.2
                                                },
                                  "1780C1070":  {
                                                    "totalt":  1852,
                                                    "andel019":  24.3,
                                                    "andel65":  19.1
                                                },
                                  "1780C1080":  {
                                                    "totalt":  1865,
                                                    "andel019":  18,
                                                    "andel65":  14.5
                                                },
                                  "1780C1090":  {
                                                    "totalt":  1605,
                                                    "andel019":  17.4,
                                                    "andel65":  22.6
                                                },
                                  "1780C1100":  {
                                                    "totalt":  1725,
                                                    "andel019":  12.6,
                                                    "andel65":  23.2
                                                },
                                  "1780C1110":  {
                                                    "totalt":  1960,
                                                    "andel019":  22.9,
                                                    "andel65":  21
                                                },
                                  "1780C1120":  {
                                                    "totalt":  1548,
                                                    "andel019":  6.8,
                                                    "andel65":  23.5
                                                },
                                  "1780C1130":  {
                                                    "totalt":  2053,
                                                    "andel019":  9.3,
                                                    "andel65":  26.5
                                                },
                                  "1780C1140":  {
                                                    "totalt":  1825,
                                                    "andel019":  9.1,
                                                    "andel65":  21.6
                                                },
                                  "1780C1150":  {
                                                    "totalt":  1817,
                                                    "andel019":  11,
                                                    "andel65":  40.3
                                                },
                                  "1780C1160":  {
                                                    "totalt":  1660,
                                                    "andel019":  18.8,
                                                    "andel65":  27.3
                                                },
                                  "1780C1170":  {
                                                    "totalt":  2095,
                                                    "andel019":  26.3,
                                                    "andel65":  26.8
                                                },
                                  "1780C1180":  {
                                                    "totalt":  2089,
                                                    "andel019":  24.6,
                                                    "andel65":  14.3
                                                },
                                  "1780C1190":  {
                                                    "totalt":  1944,
                                                    "andel019":  26.1,
                                                    "andel65":  26
                                                },
                                  "1780C1200":  {
                                                    "totalt":  1860,
                                                    "andel019":  16.5,
                                                    "andel65":  17.8
                                                },
                                  "1780C1210":  {
                                                    "totalt":  1995,
                                                    "andel019":  11.7,
                                                    "andel65":  27.3
                                                },
                                  "1780C1220":  {
                                                    "totalt":  1626,
                                                    "andel019":  13.2,
                                                    "andel65":  22.6
                                                },
                                  "1780C1230":  {
                                                    "totalt":  2015,
                                                    "andel019":  12.3,
                                                    "andel65":  19.9
                                                },
                                  "1780C1240":  {
                                                    "totalt":  1967,
                                                    "andel019":  28.2,
                                                    "andel65":  17.8
                                                },
                                  "1780C1250":  {
                                                    "totalt":  2008,
                                                    "andel019":  23.6,
                                                    "andel65":  10.6
                                                },
                                  "1780C1260":  {
                                                    "totalt":  1279,
                                                    "andel019":  22.9,
                                                    "andel65":  25.4
                                                },
                                  "1780C1270":  {
                                                    "totalt":  1858,
                                                    "andel019":  20.2,
                                                    "andel65":  27.7
                                                },
                                  "1780C1280":  {
                                                    "totalt":  1132,
                                                    "andel019":  29.4,
                                                    "andel65":  18.4
                                                },
                                  "1780C1290":  {
                                                    "totalt":  1749,
                                                    "andel019":  15.9,
                                                    "andel65":  31.3
                                                },
                                  "1780C1300":  {
                                                    "totalt":  1576,
                                                    "andel019":  20.7,
                                                    "andel65":  7.7
                                                },
                                  "1780C1310":  {
                                                    "totalt":  1606,
                                                    "andel019":  29.3,
                                                    "andel65":  18.3
                                                },
                                  "1780C1321":  {
                                                    "totalt":  751,
                                                    "andel019":  13,
                                                    "andel65":  3.2
                                                },
                                  "1780C1322":  {
                                                    "totalt":  1123,
                                                    "andel019":  25.9,
                                                    "andel65":  27.8
                                                },
                                  "1780C1330":  {
                                                    "totalt":  1516,
                                                    "andel019":  23.3,
                                                    "andel65":  14
                                                },
                                  "1780C1340":  {
                                                    "totalt":  2181,
                                                    "andel019":  24.7,
                                                    "andel65":  14.5
                                                },
                                  "1780C1350":  {
                                                    "totalt":  1391,
                                                    "andel019":  29,
                                                    "andel65":  14.8
                                                },
                                  "1780C1360":  {
                                                    "totalt":  1827,
                                                    "andel019":  29.3,
                                                    "andel65":  20.7
                                                },
                                  "1780C1370":  {
                                                    "totalt":  2525,
                                                    "andel019":  21.8,
                                                    "andel65":  6.3
                                                },
                                  "1780C1380":  {
                                                    "totalt":  2098,
                                                    "andel019":  19.6,
                                                    "andel65":  20.8
                                                },
                                  "1780C1390":  {
                                                    "totalt":  2251,
                                                    "andel019":  31.2,
                                                    "andel65":  15.9
                                                },
                                  "1780C1400":  {
                                                    "totalt":  2870,
                                                    "andel019":  36.7,
                                                    "andel65":  10.5
                                                },
                                  "1780C1410":  {
                                                    "totalt":  1247,
                                                    "andel019":  26.9,
                                                    "andel65":  18.7
                                                },
                                  "1780C1420":  {
                                                    "totalt":  2435,
                                                    "andel019":  31.6,
                                                    "andel65":  18.3
                                                },
                                  "1780C1430":  {
                                                    "totalt":  964,
                                                    "andel019":  30.4,
                                                    "andel65":  15.6
                                                }
                              },
                     "regso":  {
                                   "1780R001":  {
                                                    "totalt":  4289,
                                                    "andel019":  28.4,
                                                    "andel65":  18.9
                                                },
                                   "1780R002":  {
                                                    "totalt":  1861,
                                                    "andel019":  24.8,
                                                    "andel65":  20.7
                                                },
                                   "1780R003":  {
                                                    "totalt":  2094,
                                                    "andel019":  22.4,
                                                    "andel65":  25.4
                                                },
                                   "1780R004":  {
                                                    "totalt":  3848,
                                                    "andel019":  18.2,
                                                    "andel65":  25.6
                                                },
                                   "1780R005":  {
                                                    "totalt":  1960,
                                                    "andel019":  22.9,
                                                    "andel65":  21
                                                },
                                   "1780R006":  {
                                                    "totalt":  3524,
                                                    "andel019":  13.4,
                                                    "andel65":  22.5
                                                },
                                   "1780R007":  {
                                                    "totalt":  3322,
                                                    "andel019":  14.7,
                                                    "andel65":  21.3
                                                },
                                   "1780R008":  {
                                                    "totalt":  4042,
                                                    "andel019":  26.1,
                                                    "andel65":  26.3
                                                },
                                   "1780R009":  {
                                                    "totalt":  2015,
                                                    "andel019":  12.3,
                                                    "andel65":  19.9
                                                },
                                   "1780R010":  {
                                                    "totalt":  4040,
                                                    "andel019":  22.5,
                                                    "andel65":  9.2
                                                },
                                   "1780R011":  {
                                                    "totalt":  3585,
                                                    "andel019":  22.3,
                                                    "andel65":  9.2
                                                },
                                   "1780R012":  {
                                                    "totalt":  1879,
                                                    "andel019":  20.9,
                                                    "andel65":  18.4
                                                },
                                   "1780R013":  {
                                                    "totalt":  3572,
                                                    "andel019":  29,
                                                    "andel65":  18
                                                },
                                   "1780R014":  {
                                                    "totalt":  4264,
                                                    "andel019":  19.1,
                                                    "andel65":  20.9
                                                },
                                   "1780R015":  {
                                                    "totalt":  2130,
                                                    "andel019":  19.7,
                                                    "andel65":  27.9
                                                },
                                   "1780R016":  {
                                                    "totalt":  3484,
                                                    "andel019":  15.2,
                                                    "andel65":  20
                                                },
                                   "1780R017":  {
                                                    "totalt":  1889,
                                                    "andel019":  19,
                                                    "andel65":  31.3
                                                },
                                   "1780R018":  {
                                                    "totalt":  1852,
                                                    "andel019":  24.3,
                                                    "andel65":  19.1
                                                },
                                   "1780R019":  {
                                                    "totalt":  4044,
                                                    "andel019":  22.7,
                                                    "andel65":  20.6
                                                },
                                   "1780R020":  {
                                                    "totalt":  2670,
                                                    "andel019":  26.1,
                                                    "andel65":  19.8
                                                },
                                   "1780R021":  {
                                                    "totalt":  1478,
                                                    "andel019":  24.1,
                                                    "andel65":  20.2
                                                },
                                   "1780R022":  {
                                                    "totalt":  3684,
                                                    "andel019":  29.9,
                                                    "andel65":  18.3
                                                },
                                   "1780R023":  {
                                                    "totalt":  2251,
                                                    "andel019":  31.2,
                                                    "andel65":  15.9
                                                },
                                   "1780R024":  {
                                                    "totalt":  2870,
                                                    "andel019":  36.7,
                                                    "andel65":  10.5
                                                },
                                   "1780R025":  {
                                                    "totalt":  3809,
                                                    "andel019":  11.4,
                                                    "andel65":  33.6
                                                },
                                   "1780R026":  {
                                                    "totalt":  5430,
                                                    "andel019":  8.5,
                                                    "andel65":  24.1
                                                },
                                   "1780R027":  {
                                                    "totalt":  6184,
                                                    "andel019":  9.1,
                                                    "andel65":  21
                                                },
                                   "1780R028":  {
                                                    "totalt":  3085,
                                                    "andel019":  21,
                                                    "andel65":  25.9
                                                },
                                   "1780R029":  {
                                                    "totalt":  3747,
                                                    "andel019":  22.1,
                                                    "andel65":  20.3
                                                },
                                   "1780R030":  {
                                                    "totalt":  3757,
                                                    "andel019":  21.7,
                                                    "andel65":  26.2
                                                },
                                   "1780R031":  {
                                                    "totalt":  2340,
                                                    "andel019":  22.8,
                                                    "andel65":  20.9
                                                }
                               }
                 }
}